cf_mcp_gateway/__init__.py
cf_mcp_gateway/__main__.py
cf_mcp_gateway/config.py
cf_mcp_gateway/server.py
cf_mcp_gateway/proxy/__init__.py
cf_mcp_gateway/proxy/tool.py
cf_mcp_gateway/proxy/upstream.py
cf_mcp_gateway/services/__init__.py
cf_mcp_gateway/services/definitions.py
cf_mcp_gateway/services/registry.py
cf_mcp_gateway/transport/__init__.py
cf_mcp_gateway/transport/http.py
cf_mcp_gateway/transport/stdio.py
cf_mcp_gateway-0.2.1.dist-info/METADATA
cf_mcp_gateway-0.2.1.dist-info/WHEEL
cf_mcp_gateway-0.2.1.dist-info/entry_points.txt
cf_mcp_gateway-0.2.1.dist-info/licenses/LICENSE
cf_mcp_gateway-0.2.1.dist-info/RECORD
