Metadata-Version: 2.4
Name: cf-mcp-gateway
Version: 0.2.1
Summary: Centralized MCP Gateway for Cloudflare services
Author: Cloudflare MCP Gateway Contributors
License-Expression: MIT
License-File: LICENSE
Keywords: ai,cloudflare,gateway,llm,mcp
Classifier: Development Status :: 4 - Beta
Classifier: Intended Audience :: Developers
Classifier: License :: OSI Approved :: MIT License
Classifier: Programming Language :: Python :: 3
Classifier: Programming Language :: Python :: 3.11
Classifier: Programming Language :: Python :: 3.12
Requires-Python: >=3.11
Requires-Dist: fastmcp>=0.1.0
Requires-Dist: httpx>=0.27.0
Requires-Dist: mcp>=1.0.0
Requires-Dist: pydantic-settings>=2.0.0
Requires-Dist: pydantic>=2.0.0
Requires-Dist: starlette>=0.38.0
Requires-Dist: uvicorn>=0.30.0
